crosswalks/__init__.py
crosswalks/admin.py
crosswalks/apps.py
crosswalks/models.py
crosswalks/tests.py
crosswalks/views.py
crosswalks/migrations/0001_initial.py
crosswalks/migrations/__init__.py
datafiles/__init__.py
datafiles/admin.py
datafiles/apps.py
datafiles/df_functions.py
datafiles/df_serializers.py
datafiles/example.py
datafiles/forms.py
datafiles/models.py
datafiles/tests.py
datafiles/urls.py
datafiles/validation.py
datafiles/views.py
datafiles/migrations/0001_initial.py
datafiles/migrations/__init__.py
datasets/__init__.py
datasets/admin.py
datasets/apps.py
datasets/ds_functions.py
datasets/example.py
datasets/models.py
datasets/serializer.py
datasets/tests.py
datasets/urls.py
datasets/views.py
datasets/migrations/0001_initial.py
datasets/migrations/__init__.py
sciflow/__init__.py
sciflow/asgi.py
sciflow/functionmap.py
sciflow/gvars.py
sciflow/settings.py
sciflow/urls.py
sciflow/wsgi.py
substances/__init__.py
substances/admin.py
substances/apps.py
substances/example.py
substances/external.py
substances/forms.py
substances/models.py
substances/sub_functions.py
substances/sub_serializers.py
substances/tests.py
substances/urls.py
substances/views.py
substances/migrations/0001_initial.py
substances/migrations/__init__.py
users/__init__.py
users/admin.py
users/apps.py
users/auth0backend.py
users/forms.py
users/models.py
users/requests.py
users/tests.py
users/urls.py
users/views.py
workflow/__init__.py
workflow/apps.py
workflow/example.py
workflow/gdb_functions.py
workflow/log_functions.py
workflow/models.py
workflow/settings.py
workflow/tests.py
workflow/urls.py
workflow/views.py
workflow/wf_functions.py
sciflow-0.2.dist-info/LICENSE.txt
sciflow-0.2.dist-info/METADATA
sciflow-0.2.dist-info/WHEEL
sciflow-0.2.dist-info/top_level.txt
sciflow-0.2.dist-info/RECORD
