Metadata-Version: 2.1
Name: sciflow
Version: 0.2
Summary: An interface for management and storage of SciData JSON-LD files in a graph database
Home-page: https://github.com/ChalkLab/sciflow
Author: Dylan Johnson, Caleb Weber, Stuart Chalk
Author-email: n01448636@unf.edu, cweb1182@gmail.com, schalk@unf.edu
License: UNKNOWN
Platform: UNKNOWN
Classifier: Programming Language :: Python :: 3
Classifier: License :: OSI Approved :: MIT License
Classifier: Operating System :: OS Independent
Requires-Python: >=3.6
